{"$schema":"http://json-schema.org/draft-07/schema#","title":"Google Docs read_excerpt","description":"Read a bounded document excerpt with optional heading outline.","type":"object","additionalProperties":false,"required":["document_id"],"properties":{"document_id":{"type":"string","minLength":1,"description":"Google Docs document ID, same as the Drive file ID."},"query":{"type":["string","null"],"description":"Optional text to find. The excerpt starts near the first match when found."},"start_char":{"type":"integer","minimum":0,"description":"Character offset used when query is omitted or not found. Defaults to 0."},"max_chars":{"type":"integer","minimum":1,"maximum":20000,"description":"Maximum excerpt characters. Defaults to 4000."},"include_outline":{"type":"boolean","description":"Include compact heading outline. Defaults to true."}}}
